alibabacloud_arms20190808/__init__.py
alibabacloud_arms20190808/client.py
alibabacloud_arms20190808/models/__init__.py
alibabacloud_arms20190808/models/_add_ali_cluster_ids_to_prometheus_global_view_request.py
alibabacloud_arms20190808/models/_add_ali_cluster_ids_to_prometheus_global_view_response.py
alibabacloud_arms20190808/models/_add_ali_cluster_ids_to_prometheus_global_view_response_body.py
alibabacloud_arms20190808/models/_add_grafana_request.py
alibabacloud_arms20190808/models/_add_grafana_response.py
alibabacloud_arms20190808/models/_add_grafana_response_body.py
alibabacloud_arms20190808/models/_add_integration_request.py
alibabacloud_arms20190808/models/_add_integration_response.py
alibabacloud_arms20190808/models/_add_integration_response_body.py
alibabacloud_arms20190808/models/_add_prometheus_global_view_by_ali_cluster_ids_request.py
alibabacloud_arms20190808/models/_add_prometheus_global_view_by_ali_cluster_ids_response.py
alibabacloud_arms20190808/models/_add_prometheus_global_view_by_ali_cluster_ids_response_body.py
alibabacloud_arms20190808/models/_add_prometheus_global_view_request.py
alibabacloud_arms20190808/models/_add_prometheus_global_view_response.py
alibabacloud_arms20190808/models/_add_prometheus_global_view_response_body.py
alibabacloud_arms20190808/models/_add_prometheus_instance_request.py
alibabacloud_arms20190808/models/_add_prometheus_instance_response.py
alibabacloud_arms20190808/models/_add_prometheus_instance_response_body.py
alibabacloud_arms20190808/models/_add_prometheus_integration_request.py
alibabacloud_arms20190808/models/_add_prometheus_integration_response.py
alibabacloud_arms20190808/models/_add_prometheus_integration_response_body.py
alibabacloud_arms20190808/models/_add_recording_rule_request.py
alibabacloud_arms20190808/models/_add_recording_rule_response.py
alibabacloud_arms20190808/models/_add_recording_rule_response_body.py
alibabacloud_arms20190808/models/_add_tag_to_flink_cluster_request.py
alibabacloud_arms20190808-10.0.4.dist-info/LICENSE
alibabacloud_arms20190808-10.0.4.dist-info/METADATA
alibabacloud_arms20190808-10.0.4.dist-info/WHEEL
alibabacloud_arms20190808-10.0.4.dist-info/top_level.txt
alibabacloud_arms20190808-10.0.4.dist-info/RECORD
